django_modern_migration_fixer/__init__.py
django_modern_migration_fixer/git_cli.py
django_modern_migration_fixer/management/commands/makemigrations.py
django_modern_migration_fixer/py.typed
django_modern_migration_fixer/utils.py
django_modern_migration_fixer-0.1.2.dist-info/WHEEL
django_modern_migration_fixer-0.1.2.dist-info/METADATA
django_modern_migration_fixer-0.1.2.dist-info/RECORD
