Metadata-Version: 2.3
Name: django-modern-migration-fixer
Version: 0.1.2
Summary: Fix conflicting Django migrations (numbered) with robust git + worktree support
Keywords: django,migrations,git,worktree
Author: ResQ
Author-email: ResQ <engineering@getresq.com>
License: MIT
Classifier: Framework :: Django
Classifier: Intended Audience :: Developers
Classifier: License :: OSI Approved :: MIT License
Classifier: Programming Language :: Python :: 3
Classifier: Programming Language :: Python :: 3 :: Only
Classifier: Programming Language :: Python :: 3.10
Classifier: Programming Language :: Python :: 3.11
Classifier: Programming Language :: Python :: 3.12
Classifier: Programming Language :: Python :: 3.13
Classifier: Topic :: Software Development :: Build Tools
Requires-Dist: django>=5.2,<5.3
Requires-Dist: ruff>=0.5.0 ; extra == 'dev'
Requires-Dist: coverage[toml]>=7.5 ; extra == 'dev'
Requires-Dist: twine>=5.0.0 ; extra == 'dev'
Requires-Python: >=3.10
Project-URL: Homepage, https://github.com/getresq/django-modern-migration-fixer
Project-URL: Issues, https://github.com/getresq/django-modern-migration-fixer/issues
Project-URL: Repository, https://github.com/getresq/django-modern-migration-fixer
Provides-Extra: dev
